pyedt/__init__.py
pyedt/functions.py
pyedt/interface.py
pyedt/jit_interface.py
pyedt-0.1.5.dist-info/licenses/LICENSE
pyedt-0.1.5.dist-info/METADATA
pyedt-0.1.5.dist-info/WHEEL
pyedt-0.1.5.dist-info/top_level.txt
pyedt-0.1.5.dist-info/RECORD
