Metadata-Version: 2.4
Name: pyedt
Version: 0.1.5
Summary: Euclidian Distance Transform functions for GPU and parallel CPU
Home-page: https://pypi.org/project/pyedt/
Author: LTrace technologies
Classifier: Programming Language :: Python :: 3
Classifier: License :: OSI Approved :: MIT License
License-File: LICENSE
Requires-Dist: matplotlib>=3.5.1
Requires-Dist: numba>=0.56.2
Requires-Dist: numpy>=1.23.1
Requires-Dist: scipy>=1.8.1
Requires-Dist: pytest>=7.4.1
Dynamic: author
Dynamic: classifier
Dynamic: description
Dynamic: description-content-type
Dynamic: home-page
Dynamic: license-file
Dynamic: requires-dist
Dynamic: summary
